lib/__init__.py
lib/aryan.py
Topsis_aryan_102103235-0.0.1.dist-info/METADATA
Topsis_aryan_102103235-0.0.1.dist-info/WHEEL
Topsis_aryan_102103235-0.0.1.dist-info/top_level.txt
Topsis_aryan_102103235-0.0.1.dist-info/RECORD
